StackoverflowShangGuanyuPythonDeWenti/README.md
StackoverflowShangGuanyuPythonDeWenti/__init__.py
StackoverflowShangGuanyuPythonDeWenti/__main__.py
StackoverflowShangGuanyuPythonDeWenti/file.epub
StackoverflowShangGuanyuPythonDeWenti/index.html
StackoverflowShangGuanyuPythonDeWenti/css/__init__.py
StackoverflowShangGuanyuPythonDeWenti/css/annotations.css
StackoverflowShangGuanyuPythonDeWenti/css/main.css
StackoverflowShangGuanyuPythonDeWenti/css/normalize.css
StackoverflowShangGuanyuPythonDeWenti/css/popup.css
StackoverflowShangGuanyuPythonDeWenti/font/__init__.py
StackoverflowShangGuanyuPythonDeWenti/font/fontello.eot
StackoverflowShangGuanyuPythonDeWenti/font/fontello.svg
StackoverflowShangGuanyuPythonDeWenti/font/fontello.ttf
StackoverflowShangGuanyuPythonDeWenti/font/fontello.woff
StackoverflowShangGuanyuPythonDeWenti/img/__init__.py
StackoverflowShangGuanyuPythonDeWenti/img/annotator-glyph-sprite.png
StackoverflowShangGuanyuPythonDeWenti/img/annotator-icon-sprite.png
StackoverflowShangGuanyuPythonDeWenti/img/apple-touch-icon.png
StackoverflowShangGuanyuPythonDeWenti/img/cancelfullscreen.png
StackoverflowShangGuanyuPythonDeWenti/img/close.png
StackoverflowShangGuanyuPythonDeWenti/img/fullscreen.png
StackoverflowShangGuanyuPythonDeWenti/img/loader.gif
StackoverflowShangGuanyuPythonDeWenti/img/menu-icon.png
StackoverflowShangGuanyuPythonDeWenti/img/save.png
StackoverflowShangGuanyuPythonDeWenti/img/saved.png
StackoverflowShangGuanyuPythonDeWenti/img/settings-s.png
StackoverflowShangGuanyuPythonDeWenti/img/settings.png
StackoverflowShangGuanyuPythonDeWenti/img/star.png
StackoverflowShangGuanyuPythonDeWenti/js/__init__.py
StackoverflowShangGuanyuPythonDeWenti/js/epub.js
StackoverflowShangGuanyuPythonDeWenti/js/epub.min.js
StackoverflowShangGuanyuPythonDeWenti/js/epub.min.map
StackoverflowShangGuanyuPythonDeWenti/js/hooks.min.js
StackoverflowShangGuanyuPythonDeWenti/js/hooks.min.map
StackoverflowShangGuanyuPythonDeWenti/js/reader.js
stackoverflow_shang_guanyu_python_de_wenti-2024.3.5.0.dist-info/METADATA
stackoverflow_shang_guanyu_python_de_wenti-2024.3.5.0.dist-info/WHEEL
stackoverflow_shang_guanyu_python_de_wenti-2024.3.5.0.dist-info/entry_points.txt
stackoverflow_shang_guanyu_python_de_wenti-2024.3.5.0.dist-info/top_level.txt
stackoverflow_shang_guanyu_python_de_wenti-2024.3.5.0.dist-info/RECORD
